LICENSE
MANIFEST.in
NOTICE
README.md
requirements.txt
setup.cfg
setup.py
compiler/__init__.py
compiler/api/__init__.py
compiler/api/compiler.py
compiler/api/source/auth_key.tl
compiler/api/source/main_api.tl
compiler/api/source/sys_msgs.tl
compiler/api/template/combinator.txt
compiler/api/template/type.txt
compiler/errors/__init__.py
compiler/errors/compiler.py
compiler/errors/sort.py
compiler/errors/source/303_SEE_OTHER.tsv
compiler/errors/source/400_BAD_REQUEST.tsv
compiler/errors/source/401_UNAUTHORIZED.tsv
compiler/errors/source/403_FORBIDDEN.tsv
compiler/errors/source/406_NOT_ACCEPTABLE.tsv
compiler/errors/source/420_FLOOD.tsv
compiler/errors/source/500_INTERNAL_SERVER_ERROR.tsv
compiler/errors/source/503_SERVICE_UNAVAILABLE.tsv
compiler/errors/template/class.txt
compiler/errors/template/sub_class.txt
pixlib/__init__.py
pixlib/assistant.py
pixlib/client.py
pixlib/dispatcher.py
pixlib/emoji.py
pixlib/file_id.py
pixlib/filters.py
pixlib/mime_types.py
pixlib/py.typed
pixlib/sync.py
pixlib/utils.py
pixlib.egg-info/PKG-INFO
pixlib.egg-info/SOURCES.txt
pixlib.egg-info/dependency_links.txt
pixlib.egg-info/not-zip-safe
pixlib.egg-info/requires.txt
pixlib.egg-info/top_level.txt
pixlib/Pix/__init__.py
pixlib/Pix/_wrappers.py
pixlib/Pix/autobot.py
pixlib/Pix/filter.py
pixlib/Pix/assistant/__init__.py
pixlib/Pix/assistant/callback.py
pixlib/Pix/assistant/host.py
pixlib/Pix/database/__init__.py
pixlib/Pix/database/fitersdb.py
pixlib/Pix/database/gbandb.py
pixlib/Pix/database/global.py
pixlib/Pix/database/gmutedb.py
pixlib/Pix/database/notesdb.py
pixlib/Pix/database/pm_permit.py
pixlib/Pix/database/pmpermit.py
pixlib/Pix/database/slr.py
pixlib/Pix/database/sudodb.py
pixlib/Pix/helper/PyroHelpers.py
pixlib/Pix/helper/__init__.py
pixlib/Pix/helper/adminHelpers.py
pixlib/Pix/helper/aiohttp_helper.py
pixlib/Pix/helper/basic.py
pixlib/Pix/helper/constants.py
pixlib/Pix/helper/data.py
pixlib/Pix/helper/inline.py
pixlib/Pix/helper/inline2.py
pixlib/Pix/helper/interval.py
pixlib/Pix/helper/parser.py
pixlib/Pix/helper/pluginhelper.py
pixlib/Pix/helper/utility.py
pixlib/Pix/helper/what.py
pixlib/Pix/utils/__init__.py
pixlib/Pix/utils/extra.py
