Metadata-Version: 2.1
Name: pixlib
Version: 1.0
Summary: pixlib - Telegram MTProto API Client Library for Python.
Home-page: https://github.com/tanmaysingh3856/pixlib
Author: slr
Author-email: tanmaysingh.forwork@gmail.com
License: GNU Lesser General Public License v3.0 (LGPL-3.0)
Project-URL: Bug Tracker, https://github.com/tanmaysingh3856/pixlib/issues
Project-URL: Documentation, https://slrded.tech
Project-URL: Source Code, https://github.com/tanmaysingh3856/pixlib
Classifier: Programming Language :: Python :: 3
Classifier: Programming Language :: Python :: 3.8
Classifier: Programming Language :: Python :: 3.9
Classifier: Programming Language :: Python :: 3.10
Classifier: License :: OSI Approved :: GNU General Public License v3 (GPLv3)
Classifier: Operating System :: OS Independent
Requires-Python: ~=3.7
License-File: LICENSE
License-File: NOTICE
Requires-Dist: pyaes==1.6.1
Requires-Dist: pysocks==1.7.1
Requires-Dist: aiosqlite<0.18.0,>=0.16.0
Requires-Dist: Pillow
Requires-Dist: motor==3.0.0
Requires-Dist: requests
